sqlalchemy_orm_tree2-0.4.0.dist-info/DESCRIPTION.rst
sqlalchemy_orm_tree2-0.4.0.dist-info/METADATA
sqlalchemy_orm_tree2-0.4.0.dist-info/RECORD
sqlalchemy_orm_tree2-0.4.0.dist-info/WHEEL
sqlalchemy_orm_tree2-0.4.0.dist-info/metadata.json
sqlalchemy_orm_tree2-0.4.0.dist-info/top_level.txt
sqlalchemy_tree/__about__.py
sqlalchemy_tree/__init__.py
sqlalchemy_tree/_compat.py
sqlalchemy_tree/exceptions.py
sqlalchemy_tree/options.py
sqlalchemy_tree/orm.py
sqlalchemy_tree/types.py
sqlalchemy_tree/manager/__init__.py
sqlalchemy_tree/manager/class_.py
sqlalchemy_tree/manager/instance.py
sqlalchemy_tree/manager/unmapped.py
sqlalchemy_tree/tests/Deletion.py
sqlalchemy_tree/tests/ExplicitMove.py
sqlalchemy_tree/tests/Insert.py
sqlalchemy_tree/tests/Named.py
sqlalchemy_tree/tests/Regression.py
sqlalchemy_tree/tests/Update.py
sqlalchemy_tree/tests/__init__.py
sqlalchemy_tree/tests/helper.py
