Metadata-Version: 2.0
Name: sqlalchemy-orm-tree2
Version: 0.4.0
Summary: An implementation for SQLAlchemy-based applications of the nested-sets/modified-pre-order-tree-traversal technique for storing hierarchical data in a relational database.
Home-page: http://www.github.com/miracle2k/sqlalchemy-orm-tree/
Author: Mark Friedenbach
Author-email: mark@monetize.io
License: UNKNOWN
Platform: UNKNOWN
Classifier: Development Status :: 3 - Alpha
Classifier: Intended Audience :: Developers
Classifier: License :: OSI Approved :: BSD License
Classifier: Operating System :: OS Independent
Classifier: Programming Language :: Python
Classifier: Programming Language :: Python :: 2.6
Classifier: Programming Language :: Python :: 2.7
Classifier: Programming Language :: Python :: 3
Classifier: Programming Language :: Python :: 3.3
Classifier: Programming Language :: Python :: 3.4
Classifier: Topic :: Database
Classifier: Topic :: Software Development :: Libraries :: Python Modules
Classifier: Topic :: Utilities
Requires-Dist: SQLAlchemy (>=1.0.10)
